README.md
setup.py
Tripadvisor_Scraper_Project.egg-info/PKG-INFO
Tripadvisor_Scraper_Project.egg-info/SOURCES.txt
Tripadvisor_Scraper_Project.egg-info/dependency_links.txt
Tripadvisor_Scraper_Project.egg-info/requires.txt
Tripadvisor_Scraper_Project.egg-info/top_level.txt
tripadvisor_scraper/__init__.py
tripadvisor_scraper/__main__.py
tripadvisor_scraper/scraper.py
tripadvisor_scraper/scraper_test.py