Metadata-Version: 1.0
Name: Tripadvisor-Scraper-Project
Version: 0.0.11
Summary: Mock package that scrap data of hotels from Tripadvisor
Home-page: UNKNOWN
Author: dhaval, luqman, aicore
Author-email: UNKNOWN
License: MIT
Platform: UNKNOWN
